jcircuit/__init__.py
jcircuit/static/widget.js
jcircuit/static/assets/C.jpg
jcircuit/static/assets/C.png
jcircuit/static/assets/C_hover.jpg
jcircuit/static/assets/C_hover.png
jcircuit/static/assets/C_hover_selected.jpg
jcircuit/static/assets/C_hover_selected.png
jcircuit/static/assets/C_selected.jpg
jcircuit/static/assets/C_selected.png
jcircuit/static/assets/G.jpg
jcircuit/static/assets/G.png
jcircuit/static/assets/G_hover.jpg
jcircuit/static/assets/G_hover.png
jcircuit/static/assets/G_hover_selected.jpg
jcircuit/static/assets/G_hover_selected.png
jcircuit/static/assets/G_selected.jpg
jcircuit/static/assets/G_selected.png
jcircuit/static/assets/J.jpg
jcircuit/static/assets/J.png
jcircuit/static/assets/J_hover.jpg
jcircuit/static/assets/J_hover.png
jcircuit/static/assets/J_hover_selected.jpg
jcircuit/static/assets/J_hover_selected.png
jcircuit/static/assets/J_selected.jpg
jcircuit/static/assets/J_selected.png
jcircuit/static/assets/L.jpg
jcircuit/static/assets/L.png
jcircuit/static/assets/L_hover.jpg
jcircuit/static/assets/L_hover.png
jcircuit/static/assets/L_hover_selected.jpg
jcircuit/static/assets/L_hover_selected.png
jcircuit/static/assets/L_selected.jpg
jcircuit/static/assets/L_selected.png
jcircuit/static/assets/R.jpg
jcircuit/static/assets/R.png
jcircuit/static/assets/R_hover.jpg
jcircuit/static/assets/R_hover.png
jcircuit/static/assets/R_hover_selected.jpg
jcircuit/static/assets/R_hover_selected.png
jcircuit/static/assets/R_selected.jpg
jcircuit/static/assets/R_selected.png
jcircuit/static/assets/assets/C.jpg
jcircuit/static/assets/assets/C.png
jcircuit/static/assets/assets/C_hover.jpg
jcircuit/static/assets/assets/C_hover.png
jcircuit/static/assets/assets/C_hover_selected.jpg
jcircuit/static/assets/assets/C_hover_selected.png
jcircuit/static/assets/assets/C_selected.jpg
jcircuit/static/assets/assets/C_selected.png
jcircuit/static/assets/assets/G.jpg
jcircuit/static/assets/assets/G.png
jcircuit/static/assets/assets/G_hover.jpg
jcircuit-0.0.1.dist-info/METADATA
jcircuit-0.0.1.dist-info/WHEEL
jcircuit-0.0.1.dist-info/licenses/LICENSE
jcircuit-0.0.1.dist-info/RECORD
