Metadata-Version: 2.4
Name: jcircuit
Version: 0.0.1
License-File: LICENSE
Requires-Dist: anywidget
Requires-Dist: jupyterlab
Provides-Extra: dev
Requires-Dist: watchfiles; extra == 'dev'
